AUTHORS
LICENSE
MANIFEST.in
README.rst
setup.cfg
setup.py
pycodeexport/__init__.py
pycodeexport/_release.py
pycodeexport/codeexport.py
pycodeexport/dist.py
pycodeexport/mako_util.py
pycodeexport/util.py
pycodeexport.egg-info/PKG-INFO
pycodeexport.egg-info/SOURCES.txt
pycodeexport.egg-info/dependency_links.txt
pycodeexport.egg-info/requires.txt
pycodeexport.egg-info/top_level.txt
pycodeexport/tests/test_codeexport.py
pycodeexport/tests/test_util.py