Metadata-Version: 2.1
Name: pycodeexport
Version: 0.1.3
Summary: pycodeexport is a Python package for code generation.
Home-page: https://github.com/bjodah/pycodeexport
Author: Bjoern I. Dahlgren
Author-email: bjodah@gmail.com
License: BSD
Platform: UNKNOWN
Classifier: Development Status :: 3 - Alpha
Classifier: Intended Audience :: Developers
Classifier: License :: OSI Approved :: BSD License
Classifier: Operating System :: POSIX
Classifier: Programming Language :: Python
Classifier: Programming Language :: C
Classifier: Programming Language :: C++
Classifier: Programming Language :: Cython
Classifier: Programming Language :: Fortran
Classifier: Topic :: Software Development :: Code Generators
Classifier: Topic :: Software Development :: Compilers
Classifier: Topic :: Software Development :: Libraries :: Python Modules
Provides-Extra: all
